tefaswrapper/__init__.py
tefaswrapper/models.py
tefaswrapper/wrapper.py
tefas_wrapper-0.5.1.dist-info/LICENSE
tefas_wrapper-0.5.1.dist-info/METADATA
tefas_wrapper-0.5.1.dist-info/WHEEL
tefas_wrapper-0.5.1.dist-info/top_level.txt
tefas_wrapper-0.5.1.dist-info/RECORD
