Metadata-Version: 2.1
Name: tefas-wrapper
Version: 0.5.1
Summary: Tefas wrapper to fetch funds data from http://tefas.gov.tr/
Home-page: https://github.com/semudu/tefas-wrapper
Download-URL: https://github.com/semudu/tefas-wrapper/archive/vv0.5.1.tar.gz
Author: Serhat Mutlu Durmaz
Author-email: serhat.md@gmail.com
License: MIT
Keywords: TEFAS,WRAPPER,FUND,FON
Classifier: Development Status :: 5 - Production/Stable
Classifier: Intended Audience :: Developers
Classifier: Topic :: Software Development :: Build Tools
Classifier: License :: OSI Approved :: MIT License
Classifier: Programming Language :: Python :: 3
Classifier: Operating System :: OS Independent
Requires-Python: >=3.8
License-File: LICENSE
Requires-Dist: requests
Requires-Dist: beautifulsoup4
Requires-Dist: js2xml
Requires-Dist: marshmallow
Requires-Dist: pandas
